frinx_conductor_workers/__init__.py
frinx_conductor_workers/cli_worker.py
frinx_conductor_workers/cli_worker_test.py
frinx_conductor_workers/common_worker.py
frinx_conductor_workers/connection_manager_worker.py
frinx_conductor_workers/frinx_rest.py
frinx_conductor_workers/http_worker.py
frinx_conductor_workers/import_workflows.py
frinx_conductor_workers/logging_helpers.py
frinx_conductor_workers/netconf_worker.py
frinx_conductor_workers/netconf_worker_test.py
frinx_conductor_workers/resource_manager_worker.py
frinx_conductor_workers/uniconfig_worker.py
frinx_conductor_workers/uniconfig_worker_test.py
frinx_conductor_workers/util.py
frinx_conductor_workflows/Dynamic_fork.json
frinx_conductor_workflows/Mount_apply_template_unmount_cli.json
frinx_conductor_workflows/UC_TX_close.json
frinx_conductor_workflows/UC_TX_commit.json
frinx_conductor_workflows/UC_TX_rollback.json
frinx_conductor_workflows/UC_TX_start.json
frinx_conductor_workflows/resource_manager_workflows/Allocate_IPv4_Prefix_Resource.json
frinx_conductor_workflows/resource_manager_workflows/Allocate_IPv4_Resource.json
frinx_conductor_workflows/resource_manager_workflows/Allocate_IPv6_Prefix_Resource.json
frinx_conductor_workflows/resource_manager_workflows/Allocate_IPv6_Resource.json
frinx_conductor_workflows/resource_manager_workflows/Create_IPv4_Pool.json
frinx_conductor_workflows/resource_manager_workflows/Create_IPv4_Prefix_Pool.json
frinx_conductor_workflows/resource_manager_workflows/Create_IPv6_Pool.json
frinx_conductor_workflows/resource_manager_workflows/Create_IPv6_Prefix_Pool.json
frinx_conductor_workflows/resource_manager_workflows/Create_Subnet.json
frinx_conductor_workflows/resource_manager_workflows/Deallocate_Resource.json
frinx_conductor_workflows/resource_manager_workflows/Delete_Pool_IPv4.json
frinx_conductor_workflows/resource_manager_workflows/Delete_Pool_IPv6.json
frinx_conductor_workers-2.1.0.dist-info/METADATA
frinx_conductor_workers-2.1.0.dist-info/WHEEL
frinx_conductor_workers-2.1.0.dist-info/top_level.txt
frinx_conductor_workers-2.1.0.dist-info/RECORD
