Metadata-Version: 2.1
Name: frinx_conductor_workers
Version: 2.1.0
Summary: Conductor python client workers
Home-page: https://github.com/FRINXio/fm-base-workers
Author: Frinx
Author-email: info@frinx.io
License: Apache 2.0
Keywords: conductor
